MANIFEST.in
setup.py
scikits/__init__.py
scikits.bvp_solver.egg-info/PKG-INFO
scikits.bvp_solver.egg-info/SOURCES.txt
scikits.bvp_solver.egg-info/dependency_links.txt
scikits.bvp_solver.egg-info/namespace_packages.txt
scikits.bvp_solver.egg-info/top_level.txt
scikits.bvp_solver.egg-info/zip-safe
scikits/bvp_solver/ProblemDefinition.py
scikits/bvp_solver/Solution.py
scikits/bvp_solver/__init__.py
scikits/bvp_solver/solver.py
scikits/bvp_solver/template_generator.py
scikits/bvp_solver/tools.py
scikits/bvp_solver/examples/Example2.py
scikits/bvp_solver/examples/Example3.py
scikits/bvp_solver/examples/Example4.py
scikits/bvp_solver/examples/Example5.py
scikits/bvp_solver/examples/Example6.py
scikits/bvp_solver/examples/TemplateExample.py
scikits/bvp_solver/examples/TutorialExample.py
scikits/bvp_solver/lib/BVP_INTERFACE.f90
scikits/bvp_solver/lib/BVP_LA.f
scikits/bvp_solver/lib/BVP_LA_LicenseInfo.txt
scikits/bvp_solver/lib/BVP_M.f90
scikits/bvp_solver/lib/BVP_SOLVER_License.txt
scikits/bvp_solver/lib/bvp_interface.pyf
scikits/bvp_solver/lib/lampak.f
scikits/bvp_solver/tests/__init__.py
scikits/bvp_solver/tests/test_ProblemDefinition.py
scikits/bvp_solver/tests/test_Solution.py
scikits/bvp_solver/tests/test_get_template.py
scikits/bvp_solver/tests/test_solver.py
scikits/bvp_solver/tests/test_tools.py
scikits/bvp_solver/tests/test_examples/__init__.py
scikits/bvp_solver/tests/test_examples/example2data.py
scikits/bvp_solver/tests/test_examples/example3data.py
scikits/bvp_solver/tests/test_examples/example5data.py
scikits/bvp_solver/tests/test_examples/test_Example2.py
scikits/bvp_solver/tests/test_examples/test_Example3.py
scikits/bvp_solver/tests/test_examples/test_Example4.py
scikits/bvp_solver/tests/test_examples/test_Example5.py
scikits/bvp_solver/tests/test_examples/test_TemplateExample.py
scikits/bvp_solver/tests/test_examples/test_TutorialExample.py
scikits/bvp_solver/tests/test_examples/testing.py