Metadata-Version: 1.1
Name: scikits.bvp_solver
Version: 1.1
Summary: Python package for solving two-point boundary value problems
Home-page: http://packages.python.org/scikits.bvp_solver/
Author: John Salvatier
Author-email: jsalvatier@gmail.com
License: BSD
Platform: any
Classifier: Development Status :: 5 - Production/Stable
Classifier: Programming Language :: Python
Classifier: License :: OSI Approved :: BSD License
Classifier: Intended Audience :: Science/Research
Classifier: Topic :: Scientific/Engineering
Classifier: Topic :: Scientific/Engineering :: Mathematics
Classifier: Operating System :: OS Independent
Requires: numpy
